EmailHarvester/__init__.py
EmailHarvester/core/__init__.py
EmailHarvester/core/checks.py
EmailHarvester/core/colors.py
EmailHarvester/core/commons.py
EmailHarvester/core/launch.py
EmailHarvester/core/output.py
EmailHarvester/core/parameters.py
EmailHarvester/core/parser.py
EmailHarvester/core/plugin.py
EmailHarvester/core/plugins.py
EmailHarvester/core/settings.py
EmailHarvester/core/splash.py
EmailHarvester/plugins/__init__.py
EmailHarvester/plugins/ask.py
EmailHarvester/plugins/baidu.py
EmailHarvester/plugins/bing.py
EmailHarvester/plugins/dogpile.py
EmailHarvester/plugins/exalead.py
EmailHarvester/plugins/github.py
EmailHarvester/plugins/google.py
EmailHarvester/plugins/googleplus.py
EmailHarvester/plugins/instagram.py
EmailHarvester/plugins/linkedin.py
EmailHarvester/plugins/reddit.py
EmailHarvester/plugins/twitter.py
EmailHarvester/plugins/yahoo.py
EmailHarvester/plugins/youtube.py
EmailHarvester-2.0.1.dist-info/DESCRIPTION.rst
EmailHarvester-2.0.1.dist-info/METADATA
EmailHarvester-2.0.1.dist-info/RECORD
EmailHarvester-2.0.1.dist-info/WHEEL
EmailHarvester-2.0.1.dist-info/entry_points.txt
EmailHarvester-2.0.1.dist-info/metadata.json
EmailHarvester-2.0.1.dist-info/top_level.txt
oldmodule/__init__.py
