Metadata-Version: 2.0
Name: EmailHarvester
Version: 2.0.1
Summary: A tool to retrieve Domain email addresses from Search Engines
Home-page: https://github.com/4383/EmailHarvester
Author: Hervé Beraud
Author-email: herveberaud.pro@gmail.com
License: GNU GPL V3
Keywords: email search engines retrieve collect address
Platform: UNKNOWN
Classifier: Development Status :: 3 - Alpha
Classifier: Intended Audience :: Developers
Classifier: Topic :: Software Development :: Build Tools
Classifier: License :: OSI Approved :: GNU General Public License v3 (GPLv3)
Classifier: Programming Language :: Python :: 3
Classifier: Programming Language :: Python :: 3.3
Classifier: Programming Language :: Python :: 3.4
Classifier: Programming Language :: Python :: 3.5
Classifier: Environment :: Console
Classifier: Intended Audience :: Customer Service
Classifier: Intended Audience :: Developers
Classifier: Intended Audience :: Education
Classifier: Intended Audience :: End Users/Desktop
Classifier: Intended Audience :: Financial and Insurance Industry
Classifier: Intended Audience :: Healthcare Industry
Classifier: Intended Audience :: Information Technology
Classifier: Intended Audience :: Legal Industry
Classifier: Intended Audience :: Manufacturing
Classifier: Intended Audience :: Other Audience
Classifier: Intended Audience :: Religion
Classifier: Intended Audience :: Science/Research
Classifier: Intended Audience :: System Administrators
Classifier: Intended Audience :: Telecommunications Industry
Classifier: Natural Language :: English
Classifier: Topic :: Communications :: Email
Classifier: Topic :: Communications :: Email :: Address Book
Classifier: Topic :: Utilities
Requires-Dist: colorama
Requires-Dist: requests
Requires-Dist: termcolor
Requires-Dist: validators
Provides-Extra: dev
Requires-Dist: check-manifest; extra == 'dev'
Provides-Extra: test
Requires-Dist: coverage; extra == 'test'
